wizard/__init__.py
wizard/errors.py
wizard/expr.py
wizard/functions.py
wizard/interpreter.py
wizard/keywords.py
wizard/manager.py
wizard/mappings.py
wizard/py.typed
wizard/runner.py
wizard/scriptrunner.py
wizard/severity.py
wizard/state.py
wizard/tweaks.py
wizard/utils.py
wizard/value.py
wizard/antlr4/__init__.py
wizard/antlr4/wizardLexer.py
wizard/antlr4/wizardListener.py
wizard/antlr4/wizardParser.py
wizard/antlr4/wizardVisitor.py
wizard/contexts/__init__.py
wizard/contexts/contexts.py
wizard/contexts/factory.py
wizard/contexts/keywords.py
wizard/contexts/utils.py
bain_wizard_interpreter-1.0.3.dist-info/LICENSE
bain_wizard_interpreter-1.0.3.dist-info/METADATA
bain_wizard_interpreter-1.0.3.dist-info/WHEEL
bain_wizard_interpreter-1.0.3.dist-info/top_level.txt
bain_wizard_interpreter-1.0.3.dist-info/RECORD
