Metadata-Version: 2.1
Name: bain-wizard-interpreter
Version: 1.0.3
Summary: A BAIN Wizard Interpreter based on wizparse.
Home-page: https://github.com/Holt59/bain-wizard-interpreter
Author: Holt59
Author-email: capelle.mikael@gmail.com
License: MIT
Platform: UNKNOWN
Classifier: Programming Language :: Python
Classifier: Programming Language :: Python :: 3
Classifier: Programming Language :: Python :: 3.8
Classifier: Programming Language :: Python :: 3.9
Classifier: Programming Language :: Python :: 3.10
License-File: LICENSE
Requires-Dist: chardet
Requires-Dist: antlr4-python3-runtime (==4.10)
Provides-Extra: dev
Requires-Dist: black ; extra == 'dev'
Requires-Dist: bump2version ; extra == 'dev'
Requires-Dist: flake8-black ; extra == 'dev'
Requires-Dist: flake8 ; extra == 'dev'
Requires-Dist: isort ; extra == 'dev'
Requires-Dist: mypy ; extra == 'dev'
Requires-Dist: types-chardet ; extra == 'dev'
Provides-Extra: tests
Requires-Dist: pytest ; extra == 'tests'
